{
  "by_quintile": [
    {
      "quintile": 1,
      "label": "Q1",
      "count": 3,
      "median_income": 40962.0,
      "mae": 11.333333333333334,
      "mape": 40.94872068609658,
      "bias": -40.94872068609658,
      "mean_error_pct": -40.94872068609658
    },
    {
      "quintile": 2,
      "label": "Q2",
      "count": 3,
      "median_income": 55109.0,
      "mae": 10.666666666666666,
      "mape": 25.936941681899388,
      "bias": -25.936941681899388,
      "mean_error_pct": -25.936941681899388
    },
    {
      "quintile": 3,
      "label": "Q3",
      "count": 3,
      "median_income": 78197.0,
      "mae": 2.6666666666666665,
      "mape": 14.519140989729223,
      "bias": -12.931839402427636,
      "mean_error_pct": -12.931839402427636
    },
    {
      "quintile": 4,
      "label": "Q4",
      "count": 3,
      "median_income": 79963.0,
      "mae": 4.0,
      "mape": 10.270774976657329,
      "bias": -10.270774976657329,
      "mean_error_pct": -10.270774976657329
    },
    {
      "quintile": 5,
      "label": "Q5",
      "count": 3,
      "median_income": 124773.0,
      "mae": 7.333333333333333,
      "mape": 13.873050682261209,
      "bias": 2.4695419103313845,
      "mean_error_pct": 2.4695419103313845
    }
  ],
  "equity_gap": {
    "best_group": "5",
    "worst_group": "1",
    "best_group_mean": 2.469541910333333,
    "worst_group_mean": -40.948720686099996,
    "gap": 43.41826259643333,
    "gap_pct": -106.03081578363354,
    "statistically_significant": true,
    "p_value": 0.013272268812316058
  }
}